setup.py
cloudbackup/__init__.py
cloudbackup.egg-info/PKG-INFO
cloudbackup.egg-info/SOURCES.txt
cloudbackup.egg-info/dependency_links.txt
cloudbackup.egg-info/entry_points.txt
cloudbackup.egg-info/requires.txt
cloudbackup.egg-info/top_level.txt
cloudbackup/commands/__init__.py
cloudbackup/commands/send.py
cloudbackup/drivers/__init__.py
cloudbackup/drivers/s3/__init__.py
cloudbackup/drivers/s3/writer.py
cloudbackup/progressbar/__init__.py
cloudbackup/progressbar/compat.py
cloudbackup/progressbar/progressbar.py
cloudbackup/progressbar/widgets.py