Metadata-Version: 1.1
Name: cloudbackup
Version: 0.0.1
Summary: Upload/Restore stream from cloud storages.
Home-page: https://github.com/chibiegg/cloudbackup
Author: Youta EGUSA
Author-email: develop@chibiegg.net
License: UNKNOWN
Keywords: s3
Platform: UNKNOWN
Classifier: License :: OSI Approved :: MIT License
Classifier: Operating System :: OS Independent
Classifier: Programming Language :: Python
Classifier: Programming Language :: Python :: 3
